Workbook

Sheet Resumo
A1: Poupança x Selic x Ouro x Ibovespa x S&P 500 (em R$)
A2: Quanto R$ 100 viraram até 30/09/2026 (valores brutos, sem imposto)
A4: 25 anos: base 31/12/2000
A5: Anos de período | B5: 25.75 | C5: (de 31/12 do ano-base até 30/09/2026)
A7: Ativo | B7: R$ 100 viraram | C7: Múltiplo (x) | D7: Ao ano (CAGR) | E7: Acima da inflação (total) | F7: Acima da inflação (ao ano)
A8: Poupança | B8: ='Base 100 - 2000'!B28 -> 592.6747 | C8: =B8/100 -> 5.926747 | D8: =(B8/100)^(1/$B$5)-1 -> 0.071549621 | E8: =B8/$B$14-1 -> 0.29847296 | F8: =(B8/$B$14)^(1/$B$5)-1 -> 0.010194876
A9: CDI (Selic) | B9: ='Base 100 - 2000'!C28 -> 1835.7536 | C9: =B9/100 -> 18.357536 | D9: =(B9/100)^(1/$B$5)-1 -> 0.11964455 | E9: =B9/$B$14-1 -> 3.0218968 | F9: =(B9/$B$14)^(1/$B$5)-1 -> 0.055535989
A10: Ouro (R$) | B10: ='Base 100 - 2000'!D28 -> 4211.8625 | C10: =B10/100 -> 42.118625 | D10: =(B10/100)^(1/$B$5)-1 -> 0.1563422 | E10: =B10/$B$14-1 -> 8.2276414 | F10: =(B10/$B$14)^(1/$B$5)-1 -> 0.090132408
A11: Ibovespa | B11: ='Base 100 - 2000'!E28 -> 1221.8333 | C11: =B11/100 -> 12.218333 | D11: =(B11/100)^(1/$B$5)-1 -> 0.10208238 | E11: =B11/$B$14-1 -> 1.6768775 | F11: =(B11/$B$14)^(1/$B$5)-1 -> 0.038979388
A12: S&P 500 (R$) | B12: ='Base 100 - 2000'!F28 -> 1522.5281 | C12: =B12/100 -> 15.225281 | D12: =(B12/100)^(1/$B$5)-1 -> 0.11153941 | E12: =B12/$B$14-1 -> 2.3356605 | F12: =(B12/$B$14)^(1/$B$5)-1 -> 0.047894935
A13: Dólar | B13: ='Base 100 - 2000'!G28 -> 264.2791 | C13: =B13/100 -> 2.642791 | D13: =(B13/100)^(1/$B$5)-1 -> 0.03846243 | E13: =B13/$B$14-1 -> -0.42099896 | F13: =(B13/$B$14)^(1/$B$5)-1 -> -0.020997809
A14: IPCA (inflação) | B14: ='Base 100 - 2000'!H28 -> 456.43977 | C14: =B14/100 -> 4.5643977 | D14: =(B14/100)^(1/$B$5)-1 -> 0.060735553 | E14: =B14/$B$14-1 -> 0 | F14: =(B14/$B$14)^(1/$B$5)-1 -> 0
A17: 20 anos: base 31/12/2005
A18: Anos de período | B18: 20.75 | C18: (de 31/12 do ano-base até 30/09/2026)
A20: Ativo | B20: R$ 100 viraram | C20: Múltiplo (x) | D20: Ao ano (CAGR) | E20: Acima da inflação (total) | F20: Acima da inflação (ao ano)
A21: Poupança | B21: ='Base 100 - 2005'!B23 -> 381.20671 | C21: =B21/100 -> 3.8120671 | D21: =(B21/100)^(1/$B$18)-1 -> 0.066615123 | E21: =B21/$B$27-1 -> 0.25791909 | F21: =(B21/$B$27)^(1/$B$18)-1 -> 0.011119626
A22: CDI (Selic) | B22: ='Base 100 - 2005'!C23 -> 771.54895 | C22: =B22/100 -> 7.7154895 | D22: =(B22/100)^(1/$B$18)-1 -> 0.1034801 | E22: =B22/$B$27-1 -> 1.5459839 | F22: =(B22/$B$27)^(1/$B$18)-1 -> 0.046066535
A23: Ouro (R$) | B23: ='Base 100 - 2005'!D23 -> 1867.1543 | C23: =B23/100 -> 18.671543 | D23: =(B23/100)^(1/$B$18)-1 -> 0.15149405 | E23: =B23/$B$27-1 -> 5.1613002 | F23: =(B23/$B$27)^(1/$B$18)-1 -> 0.091582337
A24: Ibovespa | B24: ='Base 100 - 2005'!E23 -> 557.28917 | C24: =B24/100 -> 5.5728917 | D24: =(B24/100)^(1/$B$18)-1 -> 0.086314788 | E24: =B24/$B$27-1 -> 0.83896206 | F24: =(B24/$B$27)^(1/$B$18)-1 -> 0.029794327
A25: S&P 500 (R$) | B25: ='Base 100 - 2005'!F23 -> 1339.579 | C25: =B25/100 -> 13.39579 | D25: =(B25/100)^(1/$B$18)-1 -> 0.13321347 | E25: =B25/$B$27-1 -> 3.4203891 | F25: =(B25/$B$27)^(1/$B$18)-1 -> 0.074252889
A26: Dólar | B26: ='Base 100 - 2005'!G23 -> 220.48284 | C26: =B26/100 -> 2.2048284 | D26: =(B26/100)^(1/$B$18)-1 -> 0.03883885 | E26: =B26/$B$27-1 -> -0.2724431 | F26: =(B26/$B$27)^(1/$B$18)-1 -> -0.015211459
A27: IPCA (inflação) | B27: ='Base 100 - 2005'!H23 -> 303.04549 | C27: =B27/100 -> 3.0304549 | D27: =(B27/100)^(1/$B$18)-1 -> 0.054885194 | E27: =B27/$B$27-1 -> 0 | F27: =(B27/$B$27)^(1/$B$18)-1 -> 0
A30: Ibovespa e S&P 500 sem dividendos. Rentabilidade passada não garante resultado futuro. Ver aba "Fontes e notas".

Sheet Retornos anuais
A1: Ano | B1: Poupança | C1: CDI (Selic) | D1: IPCA | E1: Dólar (Ptax) | F1: Ibovespa | G1: S&P 500 (US$) | H1: Ouro (US$) | I1: S&P 500 (R$) | J1: Ouro (R$)
A2: 2000 | B2: 0.084 | C2: 0.173 | D2: 0.06 | E2: 0.093 | F2: -0.107 | G2: -0.0684 | H2: -0.0424 | I2: =(1+G2)*(1+E2)-1 -> 0.0182388 | J2: =(1+H2)*(1+E2)-1 -> 0.0466568
A3: 2001 | B3: 0.086 | C3: 0.1726 | D3: 0.077 | E3: 0.187 | F3: -0.11 | G3: -0.1398 | H3: 0.0185 | I3: =(1+G3)*(1+E3)-1 -> 0.0210574 | J3: =(1+H3)*(1+E3)-1 -> 0.2089595
A4: 2002 | B4: 0.0916 | C4: 0.1909 | D4: 0.125 | E4: 0.523 | F4: -0.17 | G4: -0.2146 | H4: 0.2029 | I4: =(1+G4)*(1+E4)-1 -> 0.1961642 | J4: =(1+H4)*(1+E4)-1 -> 0.8320167
A5: 2003 | B5: 0.1111 | C5: 0.2326 | D5: 0.093 | E5: -0.182 | F5: 0.973 | G5: 0.2018 | H5: 0.2259 | I5: =(1+G5)*(1+E5)-1 -> -0.0169276 | J5: =(1+H5)*(1+E5)-1 -> 0.0027862
A6: 2004 | B6: 0.0812 | C6: 0.1616 | D6: 0.076 | E6: -0.081 | F6: 0.178 | G6: 0.1097 | H6: 0.086 | I6: =(1+G6)*(1+E6)-1 -> 0.0198143 | J6: =(1+H6)*(1+E6)-1 -> -0.001966
A7: 2005 | B7: 0.0917 | C7: 0.19 | D7: 0.057 | E7: -0.118 | F7: 0.277 | G7: 0.0524 | H7: 0.1538 | I7: =(1+G7)*(1+E7)-1 -> -0.0717832 | J7: =(1+H7)*(1+E7)-1 -> 0.0176516
A8: 2006 | B8: 0.0832 | C8: 0.1504 | D8: 0.031 | E8: -0.087 | F8: 0.329 | G8: 0.1223 | H8: 0.2353 | I8: =(1+G8)*(1+E8)-1 -> 0.0246599 | J8: =(1+H8)*(1+E8)-1 -> 0.1278289
A9: 2007 | B9: 0.0771 | C9: 0.1181 | D9: 0.045 | E9: -0.172 | F9: 0.437 | G9: 0.0443 | H9: 0.2746 | I9: =(1+G9)*(1+E9)-1 -> -0.1353196 | J9: =(1+H9)*(1+E9)-1 -> 0.0553688
A10: 2008 | B10: 0.079 | C10: 0.1238 | D10: 0.059 | E10: 0.319 | F10: -0.412 | G10: -0.4067 | H10: 0.0162 | I10: =(1+G10)*(1+E10)-1 -> -0.2174373 | J10: =(1+H10)*(1+E10)-1 -> 0.3403678
A11: 2009 | B11: 0.0693 | C11: 0.0987 | D11: 0.043 | E11: -0.255 | F11: 0.827 | G11: 0.2653 | H11: 0.3909 | I11: =(1+G11)*(1+E11)-1 -> -0.0573515 | J11: =(1+H11)*(1+E11)-1 -> 0.0362205
A12: 2010 | B12: 0.069 | C12: 0.0976 | D12: 0.059 | E12: -0.043 | F12: 0.01 | G12: 0.1181 | H12: 0.2256 | I12: =(1+G12)*(1+E12)-1 -> 0.0700217 | J12: =(1+H12)*(1+E12)-1 -> 0.1728992
A13: 2011 | B13: 0.0743 | C13: 0.1159 | D13: 0.065 | E13: 0.126 | F13: -0.181 | G13: 0.0014 | H13: 0.179 | I13: =(1+G13)*(1+E13)-1 -> 0.1275764 | J13: =(1+H13)*(1+E13)-1 -> 0.327554
... A28: 2026* | B28: 0.0614 | C28: 0.105 | D28: 0.0395 | E28: -0.0604 | F28: 0.1565 | G28: 0.1191 | H28: 0.0023 | I28: =(1+G28)*(1+E28)-1 -> 0.05150636 | J28: =(1+H28)*(1+E28)-1 -> -0.05823892
A30: * 2026: acumulado de 31/12/2025 até 30/09/2026. Demais anos: 31/12 a 31/12.
A31: Células em azul = dados de entrada. Em preto = fórmulas. Valores em fração (0,10 = 10%).
A32: Ibovespa e S&P 500 são índices de preço (sem dividendos). CDI e poupança já incluem os juros.
A33: S&P 500 e ouro em US$ usam média mensal de dezembro (setembro em 2026), não o fechamento do dia 31. Para exatidão, troque pelos fechamentos.
A34: Detalhes das fontes na aba "Fontes e notas".

Sheet Base 100 - 2000
A1: Ano | B1: Poupança | C1: CDI (Selic) | D1: Ouro (R$) | E1: Ibovespa | F1: S&P 500 (R$) | G1: Dólar | H1: IPCA (inflação)
A2: 2000 | B2: 100 | C2: 100 | D2: 100 | E2: 100 | F2: 100 | G2: 100 | H2: 100
A3: 2001 | B3: =B2*(1+'Retornos anuais'!B3) -> 108.6 | C3: =C2*(1+'Retornos anuais'!C3) -> 117.26 | D3: =D2*(1+'Retornos anuais'!J3) -> 120.89595 | E3: =E2*(1+'Retornos anuais'!F3) -> 89 | F3: =F2*(1+'Retornos anuais'!I3) -> 102.10574 | G3: =G2*(1+'Retornos anuais'!E3) -> 118.7 | H3: =H2*(1+'Retornos anuais'!D3) -> 107.7
A4: 2002 | B4: =B3*(1+'Retornos anuais'!B4) -> 118.54776 | C4: =C3*(1+'Retornos anuais'!C4) -> 139.64493 | D4: =D3*(1+'Retornos anuais'!J4) -> 221.4834 | E4: =E3*(1+'Retornos anuais'!F4) -> 73.87 | F4: =F3*(1+'Retornos anuais'!I4) -> 122.13523 | G4: =G3*(1+'Retornos anuais'!E4) -> 180.7801 | H4: =H3*(1+'Retornos anuais'!D4) -> 121.1625
A5: 2003 | B5: =B4*(1+'Retornos anuais'!B5) -> 131.71842 | C5: =C4*(1+'Retornos anuais'!C5) -> 172.12635 | D5: =D4*(1+'Retornos anuais'!J5) -> 222.1005 | E5: =E4*(1+'Retornos anuais'!F5) -> 145.74551 | F5: =F4*(1+'Retornos anuais'!I5) -> 120.06777 | G5: =G4*(1+'Retornos anuais'!E5) -> 147.87812 | H5: =H4*(1+'Retornos anuais'!D5) -> 132.43061
A6: 2004 | B6: =B5*(1+'Retornos anuais'!B6) -> 142.41395 | C6: =C5*(1+'Retornos anuais'!C6) -> 199.94196 | D6: =D5*(1+'Retornos anuais'!J6) -> 221.66385 | E6: =E5*(1+'Retornos anuais'!F6) -> 171.68821 | F6: =F5*(1+'Retornos anuais'!I6) -> 122.44683 | G6: =G5*(1+'Retornos anuais'!E6) -> 135.89999 | H6: =H5*(1+'Retornos anuais'!D6) -> 142.49534
A7: 2005 | B7: =B6*(1+'Retornos anuais'!B7) -> 155.47331 | C7: =C6*(1+'Retornos anuais'!C7) -> 237.93094 | D7: =D6*(1+'Retornos anuais'!J7) -> 225.57657 | E7: =E6*(1+'Retornos anuais'!F7) -> 219.24585 | F7: =F6*(1+'Retornos anuais'!I7) -> 113.65721 | G7: =G6*(1+'Retornos anuais'!E7) -> 119.86379 | H7: =H6*(1+'Retornos anuais'!D7) -> 150.61757
A8: 2006 | B8: =B7*(1+'Retornos anuais'!B8) -> 168.40869 | C8: =C7*(1+'Retornos anuais'!C8) -> 273.71575 | D8: =D7*(1+'Retornos anuais'!J8) -> 254.41177 | E8: =E7*(1+'Retornos anuais'!F8) -> 291.37773 | F8: =F7*(1+'Retornos anuais'!I8) -> 116.45998 | G8: =G7*(1+'Retornos anuais'!E8) -> 109.43564 | H8: =H7*(1+'Retornos anuais'!D8) -> 155.28672
A9: 2007 | B9: =B8*(1+'Retornos anuais'!B9) -> 181.393 | C9: =C8*(1+'Retornos anuais'!C9) -> 306.04158 | D9: =D8*(1+'Retornos anuais'!J9) -> 268.49825 | E9: =E8*(1+'Retornos anuais'!F9) -> 418.7098 | F9: =F8*(1+'Retornos anuais'!I9) -> 100.70066 | G9: =G8*(1+'Retornos anuais'!E9) -> 90.612714 | H9: =H8*(1+'Retornos anuais'!D9) -> 162.27462
A10: 2008 | B10: =B9*(1+'Retornos anuais'!B10) -> 195.72305 | C10: =C9*(1+'Retornos anuais'!C10) -> 343.92953 | D10: =D9*(1+'Retornos anuais'!J10) -> 359.88641 | E10: =E9*(1+'Retornos anuais'!F10) -> 246.20136 | F10: =F9*(1+'Retornos anuais'!I10) -> 78.804584 | G10: =G9*(1+'Retornos anuais'!E10) -> 119.51817 | H10: =H9*(1+'Retornos anuais'!D10) -> 171.84882
A11: 2009 | B11: =B10*(1+'Retornos anuais'!B11) -> 209.28665 | C11: =C10*(1+'Retornos anuais'!C11) -> 377.87537 | D11: =D10*(1+'Retornos anuais'!J11) -> 372.92167 | E11: =E10*(1+'Retornos anuais'!F11) -> 449.80988 | F11: =F10*(1+'Retornos anuais'!I11) -> 74.285023 | G11: =G10*(1+'Retornos anuais'!E11) -> 89.041036 | H11: =H10*(1+'Retornos anuais'!D11) -> 179.23832
A12: 2010 | B12: =B11*(1+'Retornos anuais'!B12) -> 223.72743 | C12: =C11*(1+'Retornos anuais'!C12) -> 414.75601 | D12: =D11*(1+'Retornos anuais'!J12) -> 437.39953 | E12: =E11*(1+'Retornos anuais'!F12) -> 454.30798 | F12: =F11*(1+'Retornos anuais'!I12) -> 79.486587 | G12: =G11*(1+'Retornos anuais'!E12) -> 85.212272 | H12: =H11*(1+'Retornos anuais'!D12) -> 189.81338
A13: 2011 | B13: =B12*(1+'Retornos anuais'!B13) -> 240.35038 | C13: =C12*(1+'Retornos anuais'!C13) -> 462.82623 | D13: =D12*(1+'Retornos anuais'!J13) -> 580.6715 | E13: =E12*(1+'Retornos anuais'!F13) -> 372.07824 | F13: =F12*(1+'Retornos anuais'!I13) -> 89.627199 | G13: =G12*(1+'Retornos anuais'!E13) -> 95.949018 | H13: =H12*(1+'Retornos anuais'!D13) -> 202.15125
A14: 2012 | B14: =B13*(1+'Retornos anuais'!B14) -> 254.81948 | C14: =C13*(1+'Retornos anuais'!C14) -> 501.74991 | D14: =D13*(1+'Retornos anuais'!J14) -> 649.67768 | E14: =E13*(1+'Retornos anuais'!F14) -> 399.61203 | F14: =F13*(1+'Retornos anuais'!I14) -> 111.64924 | G14: =G13*(1+'Retornos anuais'!E14) -> 104.48848 | H14: =H13*(1+'Retornos anuais'!D14) -> 213.87603
... A28: 2026* | B28: =B27*(1+'Retornos anuais'!B28) -> 592.6747 | C28: =C27*(1+'Retornos anuais'!C28) -> 1835.7536 | D28: =D27*(1+'Retornos anuais'!J28) -> 4211.8625 | E28: =E27*(1+'Retornos anuais'!F28) -> 1221.8333 | F28: =F27*(1+'Retornos anuais'!I28) -> 1522.5281 | G28: =G27*(1+'Retornos anuais'!E28) -> 264.2791 | H28: =H27*(1+'Retornos anuais'!D28) -> 456.43977
A30: Base 100 em 31/12/2000. Cada linha = linha anterior x (1 + retorno do ano). 2026* até 30/09.

Sheet Base 100 - 2005
A1: Ano | B1: Poupança | C1: CDI (Selic) | D1: Ouro (R$) | E1: Ibovespa | F1: S&P 500 (R$) | G1: Dólar | H1: IPCA (inflação)
A2: 2005 | B2: 100 | C2: 100 | D2: 100 | E2: 100 | F2: 100 | G2: 100 | H2: 100
A3: 2006 | B3: =B2*(1+'Retornos anuais'!B8) -> 108.32 | C3: =C2*(1+'Retornos anuais'!C8) -> 115.04 | D3: =D2*(1+'Retornos anuais'!J8) -> 112.78289 | E3: =E2*(1+'Retornos anuais'!F8) -> 132.9 | F3: =F2*(1+'Retornos anuais'!I8) -> 102.46599 | G3: =G2*(1+'Retornos anuais'!E8) -> 91.3 | H3: =H2*(1+'Retornos anuais'!D8) -> 103.1
A4: 2007 | B4: =B3*(1+'Retornos anuais'!B9) -> 116.67147 | C4: =C3*(1+'Retornos anuais'!C9) -> 128.62622 | D4: =D3*(1+'Retornos anuais'!J9) -> 119.02754 | E4: =E3*(1+'Retornos anuais'!F9) -> 190.9773 | F4: =F3*(1+'Retornos anuais'!I9) -> 88.600333 | G4: =G3*(1+'Retornos anuais'!E9) -> 75.5964 | H4: =H3*(1+'Retornos anuais'!D9) -> 107.7395
A5: 2008 | B5: =B4*(1+'Retornos anuais'!B10) -> 125.88852 | C5: =C4*(1+'Retornos anuais'!C10) -> 144.55015 | D5: =D4*(1+'Retornos anuais'!J10) -> 159.54069 | E5: =E4*(1+'Retornos anuais'!F10) -> 112.29465 | F5: =F4*(1+'Retornos anuais'!I10) -> 69.335316 | G5: =G4*(1+'Retornos anuais'!E10) -> 99.711652 | H5: =H4*(1+'Retornos anuais'!D10) -> 114.09613
A6: 2009 | B6: =B5*(1+'Retornos anuais'!B11) -> 134.61259 | C6: =C5*(1+'Retornos anuais'!C11) -> 158.81725 | D6: =D5*(1+'Retornos anuais'!J11) -> 165.31933 | E6: =E5*(1+'Retornos anuais'!F11) -> 205.16233 | F6: =F5*(1+'Retornos anuais'!I11) -> 65.358832 | G6: =G5*(1+'Retornos anuais'!E11) -> 74.28518 | H6: =H5*(1+'Retornos anuais'!D11) -> 119.00226
A7: 2010 | B7: =B6*(1+'Retornos anuais'!B12) -> 143.90086 | C7: =C6*(1+'Retornos anuais'!C12) -> 174.31781 | D7: =D6*(1+'Retornos anuais'!J12) -> 193.90291 | E7: =E6*(1+'Retornos anuais'!F12) -> 207.21395 | F7: =F6*(1+'Retornos anuais'!I12) -> 69.935368 | G7: =G6*(1+'Retornos anuais'!E12) -> 71.090918 | H7: =H6*(1+'Retornos anuais'!D12) -> 126.0234
A8: 2011 | B8: =B7*(1+'Retornos anuais'!B13) -> 154.5927 | C8: =C7*(1+'Retornos anuais'!C13) -> 194.52125 | D8: =D7*(1+'Retornos anuais'!J13) -> 257.41658 | E8: =E7*(1+'Retornos anuais'!F13) -> 169.70823 | F8: =F7*(1+'Retornos anuais'!I13) -> 78.857471 | G8: =G7*(1+'Retornos anuais'!E13) -> 80.048373 | H8: =H7*(1+'Retornos anuais'!D13) -> 134.21492
A9: 2012 | B9: =B8*(1+'Retornos anuais'!B14) -> 163.89918 | C9: =C8*(1+'Retornos anuais'!C14) -> 210.88049 | D9: =D8*(1+'Retornos anuais'!J14) -> 288.00761 | E9: =E8*(1+'Retornos anuais'!F14) -> 182.26664 | F9: =F8*(1+'Retornos anuais'!I14) -> 98.233311 | G9: =G8*(1+'Retornos anuais'!E14) -> 87.172679 | H9: =H8*(1+'Retornos anuais'!D14) -> 141.99938
A10: 2013 | B10: =B9*(1+'Retornos anuais'!B15) -> 173.42172 | C10: =C9*(1+'Retornos anuais'!C15) -> 227.87745 | D10: =D9*(1+'Retornos anuais'!J15) -> 239.35713 | E10: =E9*(1+'Retornos anuais'!F15) -> 154.01531 | F10: =F9*(1+'Retornos anuais'!I15) -> 143.0833 | G10: =G9*(1+'Retornos anuais'!E15) -> 99.89989 | H10: =H9*(1+'Retornos anuais'!D15) -> 150.37735
A11: 2014 | B11: =B10*(1+'Retornos anuais'!B16) -> 185.69998 | C11: =C10*(1+'Retornos anuais'!C16) -> 252.53379 | D11: =D10*(1+'Retornos anuais'!J16) -> 266.76238 | E11: =E10*(1+'Retornos anuais'!F16) -> 149.54886 | F11: =F10*(1+'Retornos anuais'!I16) -> 184.37202 | G11: =G10*(1+'Retornos anuais'!E16) -> 113.28647 | H11: =H10*(1+'Retornos anuais'!D16) -> 160.0015
A12: 2015 | B12: =B11*(1+'Retornos anuais'!B17) -> 200.68596 | C12: =C11*(1+'Retornos anuais'!C17) -> 286.01977 | D12: =D11*(1+'Retornos anuais'!J17) -> 351.31885 | E12: =E11*(1+'Retornos anuais'!F17) -> 129.65887 | F12: =F11*(1+'Retornos anuais'!I17) -> 270.99977 | G12: =G11*(1+'Retornos anuais'!E17) -> 166.53112 | H12: =H11*(1+'Retornos anuais'!D17) -> 177.12166
A13: 2016 | B13: =B12*(1+'Retornos anuais'!B18) -> 217.3429 | C13: =C12*(1+'Retornos anuais'!C18) -> 326.03394 | D13: =D12*(1+'Retornos anuais'!J18) -> 315.44059 | E13: =E12*(1+'Retornos anuais'!F18) -> 180.09616 | F13: =F12*(1+'Retornos anuais'!I18) -> 247.48769 | G13: =G12*(1+'Retornos anuais'!E18) -> 139.05348 | H13: =H12*(1+'Retornos anuais'!D18) -> 188.28032
A14: 2017 | B14: =B13*(1+'Retornos anuais'!B19) -> 231.70926 | C14: =C13*(1+'Retornos anuais'!C19) -> 358.40911 | D14: =D13*(1+'Retornos anuais'!J19) -> 349.78812 | E14: =E13*(1+'Retornos anuais'!F19) -> 228.54203 | F14: =F13*(1+'Retornos anuais'!I19) -> 297.89809 | G14: =G13*(1+'Retornos anuais'!E19) -> 141.13929 | H14: =H13*(1+'Retornos anuais'!D19) -> 193.74045
... A23: 2026* | B23: =B22*(1+'Retornos anuais'!B28) -> 381.20671 | C23: =C22*(1+'Retornos anuais'!C28) -> 771.54895 | D23: =D22*(1+'Retornos anuais'!J28) -> 1867.1543 | E23: =E22*(1+'Retornos anuais'!F28) -> 557.28917 | F23: =F22*(1+'Retornos anuais'!I28) -> 1339.579 | G23: =G22*(1+'Retornos anuais'!E28) -> 220.48284 | H23: =H22*(1+'Retornos anuais'!D28) -> 303.04549
A25: Base 100 em 31/12/2005. Cada linha = linha anterior x (1 + retorno do ano). 2026* até 30/09.

Sheet Fontes e notas
A1: Série | B1: Fonte e observação
A2: CDI | B2: Banco Central via meusdividendos.com e renovainvest.com.br (2001 a 2025). 2000 e 2026: clubedospoupadores.com e BCB. 2026 até set: 10,50%.
A3: IPCA | B3: IBGE. 2000 a 2024: Clube dos Poupadores. 2025: 4,26%. 2026 até set: 3,95% (IPCA de setembro, divulgado em 09/10/2026).
A4: Dólar | B4: Ptax de fim de ano. 2000 a 2024: Clube dos Poupadores. 2025: R$ 5,50 contra R$ 6,19. 2026: R$ 5,17 em set/2026 (Nomad), cerca de -6,0% no ano.
A5: Ibovespa | B5: Variação do índice (sem dividendos). 2000 a 2024: Clube dos Poupadores. 2025: +33,95% (Sicredi). 2026 até 30/09: +15,65% (Seu Dinheiro).
A6: Poupança | B6: 2000 a 2012: rendimento mensal composto (iDinheiro, regra antiga). 2013 a 2025: regra atual, série BCB 195 (numerando.com.br). 2026: 9 meses compostos.
A7: S&P 500 (US$) | B7: Índice de preço, média mensal (datahub.io/core/s-and-p-500, base Shiller). Usa média de dezembro como proxy do fim do ano. Setembro em 2026.
A8: Ouro (US$) | B8: Preço por onça, média mensal (datahub.io/core/gold-prices). Mesma observação: média de dezembro como proxy. Setembro em 2026.
A9: S&P 500 e Ouro em R$ | B9: Fórmula: (1 + retorno em US$) x (1 + variação do dólar) - 1. Aproxima o que o investidor brasileiro teria com IVVB11 e GOLD11, sem custos e sem imposto.
A10: Limitações | B10: Dados anuais escondem quedas dentro do ano. Valores brutos, sem IR e sem taxas. Antes de publicar, confira os números contra o Banco Central, Yahoo Finance ou Investing.
